odoo/addons/agreement_maintenance/README.rst
odoo/addons/agreement_maintenance/__init__.py
odoo/addons/agreement_maintenance/__manifest__.py
odoo/addons/agreement_maintenance/i18n/agreement_maintenance.pot
odoo/addons/agreement_maintenance/i18n/de.po
odoo/addons/agreement_maintenance/i18n/pt.po
odoo/addons/agreement_maintenance/i18n/pt_BR.po
odoo/addons/agreement_maintenance/i18n/zh_CN.po
odoo/addons/agreement_maintenance/models/__init__.py
odoo/addons/agreement_maintenance/models/agreement.py
odoo/addons/agreement_maintenance/models/agreement_serviceprofile.py
odoo/addons/agreement_maintenance/models/maintenance_equipment.py
odoo/addons/agreement_maintenance/models/maintenance_request.py
odoo/addons/agreement_maintenance/readme/CONFIGURE.rst
odoo/addons/agreement_maintenance/readme/CONTRIBUTORS.rst
odoo/addons/agreement_maintenance/readme/CREDITS.rst
odoo/addons/agreement_maintenance/readme/DESCRIPTION.rst
odoo/addons/agreement_maintenance/readme/USAGE.rst
odoo/addons/agreement_maintenance/static/description/icon.png
odoo/addons/agreement_maintenance/static/description/index.html
odoo/addons/agreement_maintenance/views/agreement_serviceprofile_view.xml
odoo/addons/agreement_maintenance/views/agreement_view.xml
odoo/addons/agreement_maintenance/views/maintenance_equipment_view.xml
odoo/addons/agreement_maintenance/views/maintenance_request_view.xml
odoo12_addon_agreement_maintenance-12.0.1.1.1.dist-info/METADATA
odoo12_addon_agreement_maintenance-12.0.1.1.1.dist-info/WHEEL
odoo12_addon_agreement_maintenance-12.0.1.1.1.dist-info/top_level.txt
odoo12_addon_agreement_maintenance-12.0.1.1.1.dist-info/RECORD
